casers-0.11.1.dist-info/METADATA
casers-0.11.1.dist-info/WHEEL
casers-0.11.1.dist-info/entry_points.txt
casers-0.11.1.dist-info/licenses/LICENSE
casers.libs/libgcc_s-98a1ef30.so.1
casers/__init__.py
casers/__main__.py
casers/_casers.cpython-311-x86_64-linux-musl.so
casers/_casers.pyi
casers/_extra.py
casers/cli/__init__.py
casers/cli/app.py
casers/py.typed
casers/pydantic.py
casers-0.11.1.dist-info/RECORD
