Metadata-Version: 2.4
Name: casers
Version: 0.11.1
Classifier: Programming Language :: Rust
Classifier: Programming Language :: Python :: Implementation :: CPython
Classifier: Programming Language :: Python :: Implementation :: PyPy
Classifier: Programming Language :: Python :: 3
Classifier: Programming Language :: Python :: 3.8
Classifier: Programming Language :: Python :: 3.9
Classifier: Programming Language :: Python :: 3.10
Classifier: Programming Language :: Python :: 3.11
Classifier: Programming Language :: Python :: 3.12
Classifier: Programming Language :: Python :: 3.13
Classifier: Programming Language :: Python :: 3.14
Requires-Dist: pydantic>=2.0.0,<3.0.0 ; extra == 'pydantic'
Provides-Extra: pydantic
License-File: LICENSE
Summary: String case converter for Python written in Rust
Keywords: case,rust,convert cases
Author: Danil Akhtarov
Author-email: daxartio@gmail.com
Requires-Python: >=3.8
Project-URL: repository, https://github.com/daxartio/casers
Project-URL: homepage, https://pypi.org/project/casers
Project-URL: Changelog, https://github.com/daxartio/casers/blob/main/CHANGELOG.md
